{
  "projects": [
    {
      "title": "Novo projeto",
      "description": "Novo projeto testando serviço",
      "id": "6dc981c0-bc9a-46d4-b7d0-93c2b11e0fb6",
      "percent": 100,
      "createdAt": "27/05/2021"
    },
    {
      "title": "bxbxbx",
      "description": "bxcbxcbxcbxc",
      "id": "31edcc74-c6e9-4269-9656-514f1c3407a7",
      "percent": 100,
      "createdAt": "27/05/2021"
    },
    {
      "title": "gdfgdgfd",
      "description": "fgdgfdgd",
      "id": "1346f105-dbfb-45dd-962c-915740ee7a3e",
      "percent": 0,
      "createdAt": "27/05/2021"
    },
    {
      "title": "vdsvsfsfsdfsd",
      "description": "fdsfsdfsdfsfsfs fdsf dsfds",
      "id": "7006ba22-c11c-41fe-b641-69009bc0005f",
      "percent": 0,
      "createdAt": "27/05/2021"
    }
  ],
  "tasks": [
    {
      "idProject": "1346f105-dbfb-45dd-962c-915740ee7a3e",
      "id": "a573fdf4-5032-44b4-a5de-1e54222bdcfc",
      "title": "fsfsdfsd",
      "description": "fdsfsfsfsfsdfsdfds",
      "done": false
    },
    {
      "idProject": "31edcc74-c6e9-4269-9656-514f1c3407a7",
      "id": "a00ffebb-8b23-4ec4-a8da-91eafbf0c3cb",
      "title": "gfdgdgdgdgfdfgdgdgdffgdfgdgdgdgd",
      "description": "fgdgdgd fdgfdgfdgd fg dfgdgdgdgdd fdfdgdgdg",
      "done": true
    },
    {
      "idProject": "6dc981c0-bc9a-46d4-b7d0-93c2b11e0fb6",
      "id": "ad696f67-c19b-4e9c-911d-7dc0fc05c44d",
      "title": "cvxvxcvcxvcxvxv",
      "description": "vcxvxvcx cvxvxccvx vcxvxcvxc",
      "done": true
    }
  ]
}